{
    "basic_info": {
      "description_header": "Hola",
      "description": " Hola, soy Sahithi Rajaputhra, estudiante de maestr铆a en Tecnolog铆a de la Informaci贸n en la Universidad de Carolina del Norte en Charlotte, con un promedio general (CGPA) de 3.75. Tengo m谩s de dos a帽os de experiencia como Ingeniera de Software en DXC Technology, donde desarroll茅 y mantuve aplicaciones, automatiz茅 procesos y trabaj茅 en la optimizaci贸n del rendimiento del sistema. Me especializo en AS400, Java, Python y JavaScript, y tengo experiencia pr谩ctica con tecnolog铆as de desarrollo web como Node.js y MongoDB. Tambi茅n he liderado proyectos como un sistema de agricultura inteligente basado en IoT y una aplicaci贸n web de gesti贸n de eventos. Adem谩s, soy poseedora de un R茅cord Mundial Guinness en la danza con plato Tarangam y jugadora de baloncesto a nivel distrital. Gracias",
      "section_name": {
        "about": "Sobre m铆",
        "projects": "Proyectos",
        "skills": "Habilidades",
        "experience": "Experiencia"
      }
    },
    "projects": [
      {
        "title": "Smart AgroMonitor System",
        "startDate": "2022",
        "description": "Desarroll茅 un sistema de agricultura inteligente utilizando IoT para monitorear las condiciones del suelo, automatizando la recolecci贸n de datos con sensores de humedad, temperatura y humedad del aire. Se usaron Arduino, ESP8266 y aprendizaje autom谩tico en Python para optimizar el uso de recursos y predecir el rendimiento de cultivos, reduciendo los costos de mano de obra en un 80%.",
        "images": [
          "images/portfolio/animal-shelter/p1.jpg"
        ],
        "url": "",
        "technologies": [
          {
            "class": "devicon-python-plain",
            "name": "Python"
          },
          {
            "class": "devicon-firebase-plain",
            "name": "Firebase"
          },
          {
            "class": "devicon-csharp-plain",
            "name": "C#"
          }
        ]
      },
      {
        "title": "Event Chronicle",
        "startDate": "2024",
        "description": "Desarroll茅 una aplicaci贸n web para la creaci贸n y exploraci贸n de eventos usando JavaScript, Node.js, Express y MongoDB, incorporando caracter铆sticas de autenticaci贸n de usuarios y confirmaciones de asistencia (RSVP). La aplicaci贸n sigui贸 la arquitectura MVC para un c贸digo mantenible, y el dise帽o de front-end adaptable se logr贸 con HTML, CSS y EJS.",
        "images": [
          "images/portfolio/photography/p1.jpg"
        ],
        "url": "https://github.com",
        "technologies": [
          {
            "class": "devicon-node.js-original",
            "name": "Node.js"
          },
          {
            "class": "devicon-expressjs-plain",
            "name": "Express"
          },
          {
            "class": "devicon-mongodb-plain",
            "name": "MongoDB"
          },
          {
            "class": "devicon-html5-plain",
            "name": "HTML"
          },
          {
            "class": "devicon-css3-plain",
            "name": "CSS"
          },
          {
            "class": "devicon-javascript-plain",
            "name": "JavaScript"
          }
        ]
      }
      
    ],
    "experience": [
      {
        "company": "DXC Technology",
        "title": "Software Engineer",
        "years": "05.2021 - 07.2023",
        "mainTech": [
          "AS400  8/9/10"
        ],
        "technologies": [
          "AS400",
          "RxJS",
          "Node.js",
          "JavaScript",
          "Bootstrap",
          "MDBootstrap",
          "Angular Material"
        ]
      },
      {
        "company": "DXC Technology",
        "title": "Software Engineer Intern",
        "years": "01.2021 - 04.2021",
        "mainTech": [
          "AS400  8/9/10"
        ],
        "technologies": [
          "RxJS",
          "AS400  8/9/10",
          "Node.js",
          "JavaScript"
        ]
      }
    ]
  }